pibootctl/__init__.py
pibootctl/corrections.py
pibootctl/exc.py
pibootctl/files.py
pibootctl/formatter.py
pibootctl/info.py
pibootctl/main.py
pibootctl/output.py
pibootctl/parser.py
pibootctl/setting.py
pibootctl/settings.py
pibootctl/store.py
pibootctl/term.py
pibootctl/userstr.py
pibootctl-0.6.dist-info/LICENSE.txt
pibootctl-0.6.dist-info/METADATA
pibootctl-0.6.dist-info/WHEEL
pibootctl-0.6.dist-info/entry_points.txt
pibootctl-0.6.dist-info/top_level.txt
pibootctl-0.6.dist-info/RECORD
