Metadata-Version: 2.1
Name: pibootctl
Version: 0.6
Summary: Boot configuration tool for the Raspberry Pi
Home-page: UNKNOWN
Author: Dave Jones
Author-email: dave@waveform.org.uk
License: UNKNOWN
Project-URL: Documentation, https://pibootctl.readthedocs.io/
Project-URL: Source Code, https://github.com/waveform80/pibootctl
Project-URL: Issue Tracker, https://github.com/waveform80/pibootctl/issues
Keywords: raspberry pi boot
Platform: UNKNOWN
Classifier: Development Status :: 4 - Beta
Classifier: Environment :: Console
Classifier: Intended Audience :: System Administrators
Classifier: License :: OSI Approved :: GNU General Public License v3 or later (GPLv3+)
Classifier: Operating System :: POSIX :: Linux
Classifier: Programming Language :: Python
Classifier: Programming Language :: Python :: 3
Classifier: Programming Language :: Python :: 3.5
Classifier: Programming Language :: Python :: 3.6
Classifier: Programming Language :: Python :: 3.7
Classifier: Programming Language :: Python :: 3.8
Classifier: Topic :: System :: Boot
License-File: LICENSE.txt
Requires-Dist: setuptools
Requires-Dist: pkginfo
Requires-Dist: pyyaml
Provides-Extra: doc
Requires-Dist: sphinx ; extra == 'doc'
Requires-Dist: sphinx-rtd-theme ; extra == 'doc'
Provides-Extra: test
Requires-Dist: pytest ; extra == 'test'
Requires-Dist: pytest-cov ; extra == 'test'
